pyppl_notify.py
pyppl_notify-0.0.2.dist-info/LICENSE
pyppl_notify-0.0.2.dist-info/WHEEL
pyppl_notify-0.0.2.dist-info/METADATA
pyppl_notify-0.0.2.dist-info/RECORD
